array_split/__init__.py
array_split/_version.py
array_split/copyright.txt
array_split/license.py
array_split/license.txt
array_split/logging.py
array_split/split.py
array_split/split_plot.py
array_split/split_test.py
array_split/tests.py
array_split/unittest.py
array_split-0.6.5.dist-info/LICENSE.txt
array_split-0.6.5.dist-info/METADATA
array_split-0.6.5.dist-info/WHEEL
array_split-0.6.5.dist-info/top_level.txt
array_split-0.6.5.dist-info/RECORD
