Metadata-Version: 2.1
Name: array_split
Version: 0.6.5
Summary: The array_split python package is an enhancement to existing numpy.ndarray functions (such as numpy.array_split) which sub-divide a multi-dimensional array into a number of multi-dimensional sub-arrays (slices)
Author-email: Shane-J-Latham <array.split@gmail.com>, array-split <array.split@gmail.com>
License: Copyright (C) 2017 The Australian National University.
Project-URL: Homepage, https://github.com/array-split/array_split
Project-URL: Documentation, https://array-split.readthedocs.io/en/latest/
Project-URL: Repository, https://github.com/array-split/array_split
Project-URL: Issues, https://github.com/array-split/array_split/issues
Keywords: multi-dimensional-array,array,sub-array,tile,tiling,splitting,split,partition,partitioning,scipy,numpy,ndarray,domain-decomposition,array-decomposition
Classifier: Programming Language :: Python :: 3
Classifier: License :: OSI Approved :: MIT License
Classifier: Operating System :: OS Independent
Requires-Python: >=3.8
License-File: LICENSE.txt
Requires-Dist: numpy >=1.6
